i19n/__init__.py
i19n/config.py
i19n/utils.py
i19n-0.1.0.dist-info/METADATA
i19n-0.1.0.dist-info/WHEEL
i19n-0.1.0.dist-info/RECORD
