Metadata-Version: 2.1
Name: i19n
Version: 0.1.0
Summary: A simple and humanized localization library.
Home-page: https://github.com/montmorill/i19n
License: MIT
Author: montmorill
Author-email: montmorillonite@qq.com
Requires-Python: >=3.8,<4.0
Classifier: Development Status :: 2 - Pre-Alpha
Classifier: License :: OSI Approved :: MIT License
Classifier: Operating System :: OS Independent
Classifier: Programming Language :: Python :: 3
Classifier: Programming Language :: Python :: 3.8
Classifier: Programming Language :: Python :: 3.9
Classifier: Programming Language :: Python :: 3.10
Classifier: Programming Language :: Python :: 3.11
Classifier: Programming Language :: Python :: 3.12
Classifier: Topic :: Software Development :: Localization
Requires-Dist: pyyaml (>=6.0.1,<7.0.0)
Project-URL: Bug Tracker, https://github.com/montmorill/i19n/issues
Project-URL: Funding, https://montmorill.github.io/zh/sponsor
Project-URL: Repository, https://github.com/montmorill/i19n
